[{"name":"Groceries","id":0,"desc":"A simple list","items":[{"isChecked":false,"names":["Eggers","7"],"id":-1},{"isChecked":false,"names":["Milk ","15",null,null],"id":0},{"isChecked":false,"names":["Meat (sirlion)","16",null,null],"id":1},{"isChecked":false,"names":["carl","17",null,null],"id":2,"itemTemplate":"<tr class=\"item\" id=\"1\"><td class=\"completed\"><span class=\"remove-item\">Remove</span><div class=\"edit-item\"><span class=\"remove-list-item\"><img onclick=\"removeListItem(this);\" src=\"Assets/Images/Xmark.png\"</span><span class=\"edit-item\" onclick=\"editItemMenu(this);\">Edit</span></div><img onclick=\"toggleCheckMark(this);\" class=\"custom-checkbox\" src=\"Assets/Images/Xmark.png\" alt=\"Not Completed\" /></td><td class=\"Egg\">Egg</td><td class=\"7\">7</td></tr><tr class=\"item\" id=\"2\"><td class=\"completed\"><span class=\"remove-item\">Remove</span><div class=\"edit-item\"><span class=\"remove-list-item\"><img onclick=\"removeListItem(this);\" src=\"Assets/Images/Xmark.png\"</span><span class=\"edit-item\" onclick=\"editItemMenu(this);\">Edit</span></div><img onclick=\"toggleCheckMark(this);\" class=\"custom-checkbox\" src=\"Assets/Images/Xmark.png\" alt=\"Not Completed\" /></td><td class=\"Milk \">Milk </td><td class=\"15\">15</td></tr><tr class=\"item\" id=\"3\"><td class=\"completed\"><span class=\"remove-item\">Remove</span><div class=\"edit-item\"><span class=\"remove-list-item\"><img onclick=\"removeListItem(this);\" src=\"Assets/Images/Xmark.png\"</span><span class=\"edit-item\" onclick=\"editItemMenu(this);\">Edit</span></div><img onclick=\"toggleCheckMark(this);\" class=\"custom-checkbox\" src=\"Assets/Images/Xmark.png\" alt=\"Not Completed\" /></td><td class=\"Meat (sirlion)\">Meat (sirlion)</td><td class=\"16\">16</td></tr><tr class=\"item\" id=\"4\"><td class=\"completed\"><span class=\"remove-item\">Remove</span><div class=\"edit-item\"><span class=\"remove-list-item\"><img onclick=\"removeListItem(this);\" src=\"Assets/Images/Xmark.png\"</span><span class=\"edit-item\" onclick=\"editItemMenu(this);\">Edit</span></div><img onclick=\"toggleCheckMark(this);\" class=\"custom-checkbox\" src=\"Assets/Images/Xmark.png\" alt=\"Not Completed\" /></td><td class=\"carl\">carl</td><td class=\"17\">17</td></tr>"}],"keys":[{"name":"Name"},{"name":"Price","listKey":"<th class=\"keys\">Name</th><th class=\"keys\">Price</th>"}],"listTemplate":"<div class=\"list-template-container\" data-showing=\"false\" id=\"Groceries\"><div class=\"template-info\" onclick=\"toggleAddedList(this);\"><span class=\"template-name\">Groceries <span class=\"template-desc\">A simple list</span><span class=\"show-template\">></span></span><span class=\"complete-list\" onclick=\"removeList(this);\">Remove</span></div><div class=\"list-template\"><table class=\"list\"><tr class=\"key\"><th class=\"keys\"><img class=\"checkmark\" src=\"Assets/Images/CheckMark.png\" alt=\"Checkmark\" /></th></tr><tr class=\"item\"></tr></table><span onclick=\"addItem(this)\" id=\"add-item-to-list\" class=\"btn-edit\">Add Item</span><br><br><span onclick=\"setAllChecked(this);\" class=\"set-all-checked\">Set All Checked</span><span onclick=\"setAllUnchecked(this);\" class=\"set-all-unchecked\">Set All Unchecked</span><span onclick=\"showEditMenu(this)\" class=\"btn-edit\">edit</span></div></div>"}]
